{
 "datapack": [
  {
   "body": 32.51190567,
   "feedback": "acceptable",
   "hum": 81,
   "light": 26.666671753,
   "move_type": "work",
   "outdoor_des": "light intensity shower rain",
   "outdoor_hum": 88,
   "outdoor_press": 101.8,
   "outdoor_temp": 19.600000000000023,
   "press": 101.800003052,
   "set_fanspeed": 1,
   "set_temp": 18,
   "stepNo": 0,
   "temp": 25.600000381,
   "time": "2020-04-22 23:09:19.847176"
  },
  {
   "body": 33.303569794,
   "feedback": "acceptable",
   "hum": 78.300003052,
   "light": 27.5,
   "move_type": "work",
   "outdoor_des": "light intensity shower rain",
   "outdoor_hum": 88,
   "outdoor_press": 101.8,
   "outdoor_temp": 19.600000000000023,
   "press": 101.800003052,
   "set_fanspeed": 1,
   "set_temp": 18,
   "stepNo": 1,
   "temp": 25.600000381,
   "time": "2020-04-22 23:10:02.265904"
  },
  {
   "body": 33.427082062,
   "feedback": "A Bit Hot",
   "hum": 74,
   "light": 26.666671753,
   "move_type": "work",
   "outdoor_des": "light intensity shower rain",
   "outdoor_hum": 88,
   "outdoor_press": 101.8,
   "outdoor_temp": 19.600000000000023,
   "press": 101.800003052,
   "set_fanspeed": 1,
   "set_temp": 18,
   "stepNo": 2,
   "temp": 25.300001144,
   "time": "2020-04-22 23:10:38.271068"
  },
  {
   "body": 33.450000763,
   "feedback": "Comfy",
   "hum": 70.400001526,
   "light": 27.5,
   "move_type": "work",
   "outdoor_des": "light intensity shower rain",
   "outdoor_hum": 88,
   "outdoor_press": 101.8,
   "outdoor_temp": 19.600000000000023,
   "press": 101.800003052,
   "set_fanspeed": 1,
   "set_temp": 18,
   "stepNo": 3,
   "temp": 24.899999619,
   "time": "2020-04-22 23:11:17.621737"
  },
  {
   "body": 33.53125,
   "feedback": "acceptable",
   "hum": 66.599998474,
   "light": 27.5,
   "move_type": "work",
   "outdoor_des": "light intensity shower rain",
   "outdoor_hum": 88,
   "outdoor_press": 101.8,
   "outdoor_temp": 19.600000000000023,
   "press": 101.800003052,
   "set_fanspeed": 1,
   "set_temp": 18,
   "stepNo": 4,
   "temp": 24.600000381,
   "time": "2020-04-22 23:11:54.801577"
  },
  {
   "body": 33.614582062,
   "feedback": "acceptable",
   "hum": 64.300003052,
   "light": 27.5,
   "move_type": "work",
   "outdoor_des": "light intensity shower rain",
   "outdoor_hum": 88,
   "outdoor_press": 101.8,
   "outdoor_temp": 19.600000000000023,
   "press": 101.800003052,
   "set_fanspeed": 1,
   "set_temp": 18,
   "stepNo": 5,
   "temp": 24.399999619,
   "time": "2020-04-22 23:12:30.369948"
  },
  {
   "body": 33.625,
   "feedback": "acceptable",
   "hum": 61.700000763,
   "light": 27.5,
   "move_type": "work",
   "outdoor_des": "light intensity shower rain",
   "outdoor_hum": 88,
   "outdoor_press": 101.8,
   "outdoor_temp": 19.600000000000023,
   "press": 101.800003052,
   "set_fanspeed": 1,
   "set_temp": 18,
   "stepNo": 6,
   "temp": 24.200000763,
   "time": "2020-04-22 23:13:06.181863"
  },
  {
   "body": 33.587501526,
   "feedback": "acceptable",
   "hum": 60,
   "light": 28.333330154,
   "move_type": "work",
   "outdoor_des": "light intensity shower rain",
   "outdoor_hum": 88,
   "outdoor_press": 101.8,
   "outdoor_temp": 19.600000000000023,
   "press": 101.800003052,
   "set_fanspeed": 1,
   "set_temp": 18,
   "stepNo": 7,
   "temp": 24.100000381,
   "time": "2020-04-22 23:13:42.978966"
  },
  {
   "body": 33.541667938,
   "feedback": "acceptable",
   "hum": 57.799999237,
   "light": 28.333330154,
   "move_type": "work",
   "outdoor_des": "light intensity shower rain",
   "outdoor_hum": 88,
   "outdoor_press": 101.8,
   "outdoor_temp": 19.600000000000023,
   "press": 101.700004578,
   "set_fanspeed": 1,
   "set_temp": 18,
   "stepNo": 8,
   "temp": 23.899999619,
   "time": "2020-04-22 23:14:20.428316"
  },
  {
   "body": 33.395832062,
   "feedback": "A Bit Cold",
   "hum": 55.900001526,
   "light": 28.333330154,
   "move_type": "work",
   "outdoor_des": "light intensity shower rain",
   "outdoor_hum": 88,
   "outdoor_press": 101.8,
   "outdoor_temp": 19.600000000000023,
   "press": 101.800003052,
   "set_fanspeed": 1,
   "set_temp": 18,
   "stepNo": 9,
   "temp": 23.700000763,
   "time": "2020-04-22 23:14:56.240056"
  },
  {
   "body": 33.212501526,
   "feedback": "acceptable",
   "hum": 55.100002289,
   "light": 28.333330154,
   "move_type": "work",
   "outdoor_des": "light intensity shower rain",
   "outdoor_hum": 88,
   "outdoor_press": 101.8,
   "outdoor_temp": 19.600000000000023,
   "press": 101.700004578,
   "set_fanspeed": 1,
   "set_temp": 24,
   "stepNo": 10,
   "temp": 23.399999619,
   "time": "2020-04-22 23:15:32.912376"
  },
  {
   "body": 33.0546875,
   "feedback": "acceptable",
   "hum": 57.200000763,
   "light": 26.666671753,
   "move_type": "work",
   "outdoor_des": "light intensity shower rain",
   "outdoor_hum": 88,
   "outdoor_press": 101.8,
   "outdoor_temp": 19.600000000000023,
   "press": 101.700004578,
   "set_fanspeed": 1,
   "set_temp": 24,
   "stepNo": 11,
   "temp": 23.300001144,
   "time": "2020-04-22 23:16:15.659922"
  },
  {
   "body": 33.037498474,
   "feedback": "Comfy",
   "hum": 62.700000763,
   "light": 26.666671753,
   "move_type": "work",
   "outdoor_des": "light intensity shower rain",
   "outdoor_hum": 88,
   "outdoor_press": 101.8,
   "outdoor_temp": 19.600000000000023,
   "press": 101.700004578,
   "set_fanspeed": 1,
   "set_temp": 24,
   "stepNo": 12,
   "temp": 23.300001144,
   "time": "2020-04-22 23:16:50.422034"
  },
  {
   "body": 33.052082062,
   "feedback": "acceptable",
   "hum": 65.700004578,
   "light": 27.5,
   "move_type": "work",
   "outdoor_des": "light intensity shower rain",
   "outdoor_hum": 88,
   "outdoor_press": 101.8,
   "outdoor_temp": 19.600000000000023,
   "press": 101.700004578,
   "set_fanspeed": 1,
   "set_temp": 24,
   "stepNo": 13,
   "temp": 23.399999619,
   "time": "2020-04-22 23:17:24.989198"
  },
  {
   "body": 33.012500763,
   "feedback": "acceptable",
   "hum": 69.200004578,
   "light": 26.666671753,
   "move_type": "work",
   "outdoor_des": "light intensity shower rain",
   "outdoor_hum": 88,
   "outdoor_press": 101.8,
   "outdoor_temp": 19.600000000000023,
   "press": 101.800003052,
   "set_fanspeed": 1,
   "set_temp": 24,
   "stepNo": 14,
   "temp": 23.5,
   "time": "2020-04-22 23:18:01.120410"
  },
  {
   "body": 33.041667938,
   "feedback": "acceptable",
   "hum": 70.900001526,
   "light": 26.666671753,
   "move_type": "work",
   "outdoor_des": "light intensity shower rain",
   "outdoor_hum": 88,
   "outdoor_press": 101.8,
   "outdoor_temp": 19.600000000000023,
   "press": 101.700004578,
   "set_fanspeed": 1,
   "set_temp": 24,
   "stepNo": 15,
   "temp": 23.700000763,
   "time": "2020-04-22 23:18:35.882357"
  },
  {
   "body": 33.0625,
   "feedback": "acceptable",
   "hum": 72.700004578,
   "light": 26.666671753,
   "move_type": "work",
   "outdoor_des": "light intensity shower rain",
   "outdoor_hum": 88,
   "outdoor_press": 101.8,
   "outdoor_temp": 19.600000000000023,
   "press": 101.700004578,
   "set_fanspeed": 1,
   "set_temp": 24,
   "stepNo": 16,
   "temp": 23.800001144,
   "time": "2020-04-22 23:19:13.362233"
  },
  {
   "body": 33.166667938,
   "feedback": "acceptable",
   "hum": 74.400001526,
   "light": 27.5,
   "move_type": "work",
   "outdoor_des": "light intensity shower rain",
   "outdoor_hum": 88,
   "outdoor_press": 101.8,
   "outdoor_temp": 19.600000000000023,
   "press": 101.700004578,
   "set_fanspeed": 1,
   "set_temp": 24,
   "stepNo": 17,
   "temp": 23.899999619,
   "time": "2020-04-22 23:19:49.231752"
  },
  {
   "body": 33.333332062,
   "feedback": "acceptable",
   "hum": 75.300003052,
   "light": 27.5,
   "move_type": "work",
   "outdoor_des": "light intensity shower rain",
   "outdoor_hum": 88,
   "outdoor_press": 101.8,
   "outdoor_temp": 19.600000000000023,
   "press": 101.700004578,
   "set_fanspeed": 1,
   "set_temp": 24,
   "stepNo": 18,
   "temp": 24.100000381,
   "time": "2020-04-22 23:20:23.798592"
  },
  {
   "body": 33.450000763,
   "feedback": "acceptable",
   "hum": 76.099998474,
   "light": 27.5,
   "move_type": "work",
   "outdoor_des": "light intensity shower rain",
   "outdoor_hum": 88,
   "outdoor_press": 101.8,
   "outdoor_temp": 19.730000000000018,
   "press": 101.700004578,
   "set_fanspeed": 1,
   "set_temp": 24,
   "stepNo": 19,
   "temp": 24.100000381,
   "time": "2020-04-22 23:21:00.277210"
  },
  {
   "body": 33.541667938,
   "feedback": "acceptable",
   "hum": 77.200004578,
   "light": 27.5,
   "move_type": "work",
   "outdoor_des": "light intensity shower rain",
   "outdoor_hum": 88,
   "outdoor_press": 101.8,
   "outdoor_temp": 19.730000000000018,
   "press": 101.800003052,
   "set_fanspeed": 3,
   "set_temp": 18,
   "stepNo": 20,
   "temp": 24.200000763,
   "time": "2020-04-22 23:21:36.684747"
  },
  {
   "body": 33.642856598,
   "feedback": "acceptable",
   "hum": 73.5,
   "light": 27.5,
   "move_type": "work",
   "outdoor_des": "light intensity shower rain",
   "outdoor_hum": 88,
   "outdoor_press": 101.8,
   "outdoor_temp": 19.730000000000018,
   "press": 101.700004578,
   "set_fanspeed": 3,
   "set_temp": 18,
   "stepNo": 21,
   "temp": 24.100000381,
   "time": "2020-04-22 23:22:22.098823"
  },
  {
   "body": 33.6875,
   "feedback": "acceptable",
   "hum": 68.599998474,
   "light": 27.5,
   "move_type": "work",
   "outdoor_des": "light intensity shower rain",
   "outdoor_hum": 88,
   "outdoor_press": 101.8,
   "outdoor_temp": 19.730000000000018,
   "press": 101.700004578,
   "set_fanspeed": 3,
   "set_temp": 18,
   "stepNo": 22,
   "temp": 23.800001144,
   "time": "2020-04-22 23:22:58.925365"
  },
  {
   "body": 33.662498474,
   "feedback": "A Bit Cold",
   "hum": 65.5,
   "light": 26.666671753,
   "move_type": "work",
   "outdoor_des": "light intensity shower rain",
   "outdoor_hum": 88,
   "outdoor_press": 101.8,
   "outdoor_temp": 19.730000000000018,
   "press": 101.700004578,
   "set_fanspeed": 3,
   "set_temp": 18,
   "stepNo": 23,
   "temp": 23.600000381,
   "time": "2020-04-22 23:23:33.600212"
  },
  {
   "body": 33.583332062,
   "feedback": "acceptable",
   "hum": 62.5,
   "light": 26.666671753,
   "move_type": "work",
   "outdoor_des": "light intensity shower rain",
   "outdoor_hum": 88,
   "outdoor_press": 101.8,
   "outdoor_temp": 19.730000000000018,
   "press": 101.700004578,
   "set_fanspeed": 3,
   "set_temp": 18,
   "stepNo": 24,
   "temp": 23.200000763,
   "time": "2020-04-22 23:24:08.648869"
  },
  {
   "body": 33.5625,
   "feedback": "acceptable",
   "hum": 60.799999237,
   "light": 26.666671753,
   "move_type": "work",
   "outdoor_des": "light intensity shower rain",
   "outdoor_hum": 88,
   "outdoor_press": 101.8,
   "outdoor_temp": 19.730000000000018,
   "press": 101.700004578,
   "set_fanspeed": 3,
   "set_temp": 18,
   "stepNo": 25,
   "temp": 22.899999619,
   "time": "2020-04-22 23:24:43.922717"
  },
  {
   "body": 33.552082062,
   "feedback": "A Bit Cold",
   "hum": 59.299999237,
   "light": 26.666671753,
   "move_type": "work",
   "outdoor_des": "light intensity shower rain",
   "outdoor_hum": 88,
   "outdoor_press": 101.8,
   "outdoor_temp": 19.730000000000018,
   "press": 101.700004578,
   "set_fanspeed": 3,
   "set_temp": 18,
   "stepNo": 26,
   "temp": 22.5,
   "time": "2020-04-22 23:25:20.030467"
  },
  {
   "body": 33.525001526,
   "feedback": "acceptable",
   "hum": 57.900001526,
   "light": 26.666671753,
   "move_type": "work",
   "outdoor_des": "light intensity shower rain",
   "outdoor_hum": 88,
   "outdoor_press": 101.8,
   "outdoor_temp": 19.730000000000018,
   "press": 101.700004578,
   "set_fanspeed": 3,
   "set_temp": 18,
   "stepNo": 27,
   "temp": 22.200000763,
   "time": "2020-04-22 23:25:56.566522"
  },
  {
   "body": 33.458332062,
   "feedback": "acceptable",
   "hum": 57.200000763,
   "light": 27.5,
   "move_type": "work",
   "outdoor_des": "light intensity shower rain",
   "outdoor_hum": 88,
   "outdoor_press": 101.8,
   "outdoor_temp": 19.730000000000018,
   "press": 101.700004578,
   "set_fanspeed": 3,
   "set_temp": 18,
   "stepNo": 28,
   "temp": 22,
   "time": "2020-04-22 23:26:31.409145"
  },
  {
   "body": 33.375,
   "feedback": "A Bit Cold",
   "hum": 56.200000763,
   "light": 26.666671753,
   "move_type": "work",
   "outdoor_des": "light intensity shower rain",
   "outdoor_hum": 88,
   "outdoor_press": 101.8,
   "outdoor_temp": 19.730000000000018,
   "press": 101.700004578,
   "set_fanspeed": 3,
   "set_temp": 18,
   "stepNo": 29,
   "temp": 21.800001144,
   "time": "2020-04-22 23:27:08.461319"
  },
  {
   "body": 33.239582062,
   "feedback": "Cold",
   "hum": 56,
   "light": 27.5,
   "move_type": "work",
   "outdoor_des": "light intensity shower rain",
   "outdoor_hum": 88,
   "outdoor_press": 101.8,
   "outdoor_temp": 19.730000000000018,
   "press": 101.700004578,
   "set_fanspeed": 1,
   "set_temp": 25,
   "stepNo": 30,
   "temp": 21.700000763,
   "time": "2020-04-22 23:27:44.315093"
  },
  {
   "body": 33.125,
   "feedback": "acceptable",
   "hum": 58.5,
   "light": 27.5,
   "move_type": "work",
   "outdoor_des": "light intensity shower rain",
   "outdoor_hum": 88,
   "outdoor_press": 101.8,
   "outdoor_temp": 19.730000000000018,
   "press": 101.700004578,
   "set_fanspeed": 1,
   "set_temp": 25,
   "stepNo": 31,
   "temp": 21.600000381,
   "time": "2020-04-22 23:28:27.545729"
  },
  {
   "body": 33.037498474,
   "feedback": "A Bit Cold",
   "hum": 63.299999237,
   "light": 26.666671753,
   "move_type": "work",
   "outdoor_des": "light intensity shower rain",
   "outdoor_hum": 88,
   "outdoor_press": 101.8,
   "outdoor_temp": 19.730000000000018,
   "press": 101.700004578,
   "set_fanspeed": 1,
   "set_temp": 25,
   "stepNo": 32,
   "temp": 21.800001144,
   "time": "2020-04-22 23:29:02.736218"
  },
  {
   "body": 33,
   "feedback": "Comfy",
   "hum": 67.200004578,
   "light": 26.666671753,
   "move_type": "work",
   "outdoor_des": "light intensity shower rain",
   "outdoor_hum": 88,
   "outdoor_press": 101.8,
   "outdoor_temp": 19.730000000000018,
   "press": 101.800003052,
   "set_fanspeed": 1,
   "set_temp": 25,
   "stepNo": 33,
   "temp": 22.100000381,
   "time": "2020-04-22 23:29:40.702964"
  },
  {
   "body": 33,
   "feedback": "acceptable",
   "hum": 70.099998474,
   "light": 26.666671753,
   "move_type": "work",
   "outdoor_des": "light intensity shower rain",
   "outdoor_hum": 88,
   "outdoor_press": 101.8,
   "outdoor_temp": 19.730000000000018,
   "press": 101.700004578,
   "set_fanspeed": 1,
   "set_temp": 25,
   "stepNo": 34,
   "temp": 22.399999619,
   "time": "2020-04-22 23:30:17.676216"
  },
  {
   "body": 33,
   "feedback": "acceptable",
   "hum": 71.5,
   "light": 26.666671753,
   "move_type": "work",
   "outdoor_des": "light intensity shower rain",
   "outdoor_hum": 88,
   "outdoor_press": 101.8,
   "outdoor_temp": 19.730000000000018,
   "press": 101.700004578,
   "set_fanspeed": 1,
   "set_temp": 25,
   "stepNo": 35,
   "temp": 22.5,
   "time": "2020-04-22 23:30:54.426779"
  },
  {
   "body": 33.020832062,
   "feedback": "acceptable",
   "hum": 73.5,
   "light": 27.5,
   "move_type": "work",
   "outdoor_des": "light intensity shower rain",
   "outdoor_hum": 94,
   "outdoor_press": 101.7,
   "outdoor_temp": 19.730000000000018,
   "press": 101.800003052,
   "set_fanspeed": 1,
   "set_temp": 25,
   "stepNo": 36,
   "temp": 22.700000763,
   "time": "2020-04-22 23:31:29.735389"
  },
  {
   "body": 33.0625,
   "feedback": "acceptable",
   "hum": 74.300003052,
   "light": 27.5,
   "move_type": "work",
   "outdoor_des": "light intensity shower rain",
   "outdoor_hum": 94,
   "outdoor_press": 101.7,
   "outdoor_temp": 19.730000000000018,
   "press": 101.800003052,
   "set_fanspeed": 1,
   "set_temp": 25,
   "stepNo": 37,
   "temp": 22.899999619,
   "time": "2020-04-22 23:32:06.751423"
  },
  {
   "body": 33.072917938,
   "feedback": "acceptable",
   "hum": 75.5,
   "light": 27.5,
   "move_type": "work",
   "outdoor_des": "light intensity shower rain",
   "outdoor_hum": 94,
   "outdoor_press": 101.7,
   "outdoor_temp": 19.730000000000018,
   "press": 101.800003052,
   "set_fanspeed": 1,
   "set_temp": 25,
   "stepNo": 38,
   "temp": 23.100000381,
   "time": "2020-04-22 23:32:43.180308"
  },
  {
   "body": 33.087501526,
   "feedback": "Comfy",
   "hum": 76.400001526,
   "light": 27.5,
   "move_type": "work",
   "outdoor_des": "light intensity shower rain",
   "outdoor_hum": 94,
   "outdoor_press": 101.7,
   "outdoor_temp": 19.730000000000018,
   "press": 101.800003052,
   "set_fanspeed": 1,
   "set_temp": 25,
   "stepNo": 39,
   "temp": 23.200000763,
   "time": "2020-04-22 23:33:18.021016"
  },
  {
   "body": 33.125,
   "feedback": "acceptable",
   "hum": 77.400001526,
   "light": 26.666671753,
   "move_type": "work",
   "outdoor_des": "light intensity shower rain",
   "outdoor_hum": 94,
   "outdoor_press": 101.7,
   "outdoor_temp": 19.730000000000018,
   "press": 101.800003052,
   "set_fanspeed": 1,
   "set_temp": 24,
   "stepNo": 40,
   "temp": 23.300001144,
   "time": "2020-04-22 23:33:53.663391"
  },
  {
   "body": 33.133930206,
   "feedback": "acceptable",
   "hum": 78.099998474,
   "light": 27.5,
   "move_type": "work",
   "outdoor_des": "light intensity shower rain",
   "outdoor_hum": 94,
   "outdoor_press": 101.7,
   "outdoor_temp": 19.730000000000018,
   "press": 101.700004578,
   "set_fanspeed": 1,
   "set_temp": 24,
   "stepNo": 41,
   "temp": 23.5,
   "time": "2020-04-22 23:34:37.288501"
  },
  {
   "body": 33.1875,
   "feedback": "acceptable",
   "hum": 78.800003052,
   "light": 27.5,
   "move_type": "work",
   "outdoor_des": "light intensity shower rain",
   "outdoor_hum": 94,
   "outdoor_press": 101.7,
   "outdoor_temp": 19.730000000000018,
   "press": 101.700004578,
   "set_fanspeed": 1,
   "set_temp": 24,
   "stepNo": 42,
   "temp": 23.5,
   "time": "2020-04-22 23:35:14.202103"
  },
  {
   "body": 33.21875,
   "feedback": "acceptable",
   "hum": 79.200004578,
   "light": 27.5,
   "move_type": "work",
   "outdoor_des": "light intensity shower rain",
   "outdoor_hum": 94,
   "outdoor_press": 101.7,
   "outdoor_temp": 19.730000000000018,
   "press": 101.700004578,
   "set_fanspeed": 1,
   "set_temp": 24,
   "stepNo": 43,
   "temp": 23.600000381,
   "time": "2020-04-22 23:35:52.433487"
  },
  {
   "body": 33.34375,
   "feedback": "acceptable",
   "hum": 79.800003052,
   "light": 27.5,
   "move_type": "work",
   "outdoor_des": "light intensity shower rain",
   "outdoor_hum": 94,
   "outdoor_press": 101.7,
   "outdoor_temp": 19.730000000000018,
   "press": 101.700004578,
   "set_fanspeed": 1,
   "set_temp": 24,
   "stepNo": 44,
   "temp": 23.700000763,
   "time": "2020-04-22 23:36:28.797666"
  },
  {
   "body": 33.474998474,
   "feedback": "acceptable",
   "hum": 79.900001526,
   "light": 27.5,
   "move_type": "work",
   "outdoor_des": "light intensity shower rain",
   "outdoor_hum": 94,
   "outdoor_press": 101.7,
   "outdoor_temp": 19.730000000000018,
   "press": 101.700004578,
   "set_fanspeed": 1,
   "set_temp": 24,
   "stepNo": 45,
   "temp": 23.700000763,
   "time": "2020-04-22 23:37:07.312179"
  },
  {
   "body": 33.583332062,
   "feedback": "Comfy",
   "hum": 80.200004578,
   "light": 27.5,
   "move_type": "work",
   "outdoor_des": "light intensity shower rain",
   "outdoor_hum": 94,
   "outdoor_press": 101.7,
   "outdoor_temp": 19.730000000000018,
   "press": 101.700004578,
   "set_fanspeed": 1,
   "set_temp": 24,
   "stepNo": 46,
   "temp": 23.800001144,
   "time": "2020-04-22 23:37:44.026754"
  },
  {
   "body": 33.697917938,
   "feedback": "acceptable",
   "hum": 80.700004578,
   "light": 27.5,
   "move_type": "work",
   "outdoor_des": "light intensity shower rain",
   "outdoor_hum": 94,
   "outdoor_press": 101.7,
   "outdoor_temp": 19.730000000000018,
   "press": 101.700004578,
   "set_fanspeed": 1,
   "set_temp": 24,
   "stepNo": 47,
   "temp": 23.800001144,
   "time": "2020-04-22 23:38:22.467727"
  },
  {
   "body": 33.791667938,
   "feedback": "acceptable",
   "hum": 80.900001526,
   "light": 27.5,
   "move_type": "work",
   "outdoor_des": "light intensity shower rain",
   "outdoor_hum": 94,
   "outdoor_press": 101.7,
   "outdoor_temp": 19.730000000000018,
   "press": 101.700004578,
   "set_fanspeed": 1,
   "set_temp": 24,
   "stepNo": 48,
   "temp": 23.899999619,
   "time": "2020-04-22 23:39:01.327669"
  },
  {
   "body": 33.885417938,
   "feedback": "acceptable",
   "hum": 81.200004578,
   "light": 27.5,
   "move_type": "work",
   "outdoor_des": "light intensity shower rain",
   "outdoor_hum": 94,
   "outdoor_press": 101.7,
   "outdoor_temp": 19.730000000000018,
   "press": 101.700004578,
   "set_fanspeed": 1,
   "set_temp": 24,
   "stepNo": 49,
   "temp": 24,
   "time": "2020-04-22 23:39:38.419666"
  },
  {
   "body": 33.950000763,
   "feedback": "acceptable",
   "hum": 81.200004578,
   "light": 27.5,
   "move_type": "work",
   "outdoor_des": "light intensity shower rain",
   "outdoor_hum": 94,
   "outdoor_press": 101.7,
   "outdoor_temp": 19.730000000000018,
   "press": 101.700004578,
   "set_fanspeed": 2,
   "set_temp": 18,
   "stepNo": 50,
   "temp": 24,
   "time": "2020-04-22 23:40:13.993881"
  },
  {
   "body": 34,
   "feedback": "acceptable",
   "hum": 77.900001526,
   "light": 26.666671753,
   "move_type": "work",
   "outdoor_des": "light intensity shower rain",
   "outdoor_hum": 94,
   "outdoor_press": 101.7,
   "outdoor_temp": 19.730000000000018,
   "press": 101.700004578,
   "set_fanspeed": 2,
   "set_temp": 18,
   "stepNo": 51,
   "temp": 24,
   "time": "2020-04-22 23:40:54.641856"
  },
  {
   "body": 34,
   "feedback": "acceptable",
   "hum": 71.599998474,
   "light": 26.666671753,
   "move_type": "work",
   "outdoor_des": "light intensity shower rain",
   "outdoor_hum": 94,
   "outdoor_press": 101.7,
   "outdoor_temp": 19.730000000000018,
   "press": 101.700004578,
   "set_fanspeed": 2,
   "set_temp": 18,
   "stepNo": 52,
   "temp": 23.700000763,
   "time": "2020-04-22 23:41:31.326626"
  },
  {
   "body": 33.989582062,
   "feedback": "acceptable",
   "hum": 67.900001526,
   "light": 27.5,
   "move_type": "work",
   "outdoor_des": "light intensity shower rain",
   "outdoor_hum": 94,
   "outdoor_press": 101.7,
   "outdoor_temp": 19.730000000000018,
   "press": 101.700004578,
   "set_fanspeed": 2,
   "set_temp": 18,
   "stepNo": 53,
   "temp": 23.200000763,
   "time": "2020-04-22 23:42:09.336194"
  },
  {
   "body": 34.041667938,
   "feedback": "acceptable",
   "hum": 64.700004578,
   "light": 27.5,
   "move_type": "work",
   "outdoor_des": "light intensity shower rain",
   "outdoor_hum": 94,
   "outdoor_press": 101.7,
   "outdoor_temp": 19.730000000000018,
   "press": 101.700004578,
   "set_fanspeed": 2,
   "set_temp": 18,
   "stepNo": 54,
   "temp": 22.899999619,
   "time": "2020-04-22 23:42:46.118836"
  },
  {
   "body": 33.875,
   "feedback": "acceptable",
   "hum": 62.600002289,
   "light": 27.5,
   "move_type": "work",
   "outdoor_des": "light intensity shower rain",
   "outdoor_hum": 94,
   "outdoor_press": 101.7,
   "outdoor_temp": 19.730000000000018,
   "press": 101.700004578,
   "set_fanspeed": 2,
   "set_temp": 18,
   "stepNo": 55,
   "temp": 22.600000381,
   "time": "2020-04-22 23:43:23.686756"
  },
  {
   "body": 33.75,
   "feedback": "A Bit Cold",
   "hum": 60.200000763,
   "light": 26.666671753,
   "move_type": "work",
   "outdoor_des": "light intensity shower rain",
   "outdoor_hum": 94,
   "outdoor_press": 101.7,
   "outdoor_temp": 19.730000000000018,
   "press": 101.700004578,
   "set_fanspeed": 2,
   "set_temp": 18,
   "stepNo": 56,
   "temp": 22.200000763,
   "time": "2020-04-22 23:44:01.476209"
  },
  {
   "body": 33.712501526,
   "feedback": "acceptable",
   "hum": 59.400001526,
   "light": 27.5,
   "move_type": "work",
   "outdoor_des": "light intensity shower rain",
   "outdoor_hum": 94,
   "outdoor_press": 101.7,
   "outdoor_temp": 19.730000000000018,
   "press": 101.700004578,
   "set_fanspeed": 2,
   "set_temp": 18,
   "stepNo": 57,
   "temp": 21.899999619,
   "time": "2020-04-22 23:44:36.930953"
  },
  {
   "body": 33.645832062,
   "feedback": "A Bit Cold",
   "hum": 58,
   "light": 27.5,
   "move_type": "work",
   "outdoor_des": "light intensity shower rain",
   "outdoor_hum": 94,
   "outdoor_press": 101.7,
   "outdoor_temp": 19.730000000000018,
   "press": 101.700004578,
   "set_fanspeed": 2,
   "set_temp": 18,
   "stepNo": 58,
   "temp": 21.800001144,
   "time": "2020-04-22 23:45:15.053210"
  },
  {
   "body": 33.572917938,
   "feedback": "Cold",
   "hum": 56.799999237,
   "light": 27.5,
   "move_type": "work",
   "outdoor_des": "light intensity shower rain",
   "outdoor_hum": 94,
   "outdoor_press": 101.7,
   "outdoor_temp": 19.730000000000018,
   "press": 101.700004578,
   "set_fanspeed": 2,
   "set_temp": 18,
   "stepNo": 59,
   "temp": 21.600000381,
   "time": "2020-04-22 23:45:52.765602"
  },
  {
   "body": 33.520832062,
   "feedback": "acceptable",
   "hum": 56,
   "light": 27.5,
   "move_type": "work",
   "outdoor_des": "light intensity shower rain",
   "outdoor_hum": 94,
   "outdoor_press": 101.7,
   "outdoor_temp": 20.04000000000002,
   "press": 101.700004578,
   "set_fanspeed": 3,
   "set_temp": 24,
   "stepNo": 60,
   "temp": 21.5,
   "time": "2020-04-22 23:46:29.312548"
  },
  {
   "body": 33.5,
   "feedback": "A Bit Cold",
   "hum": 58.400001526,
   "light": 26.666671753,
   "move_type": "work",
   "outdoor_des": "light intensity shower rain",
   "outdoor_hum": 94,
   "outdoor_press": 101.7,
   "outdoor_temp": 20.04000000000002,
   "press": 101.700004578,
   "set_fanspeed": 3,
   "set_temp": 24,
   "stepNo": 61,
   "temp": 21.399999619,
   "time": "2020-04-22 23:47:10.880400"
  },
  {
   "body": 33.447917938,
   "feedback": "acceptable",
   "hum": 64.400001526,
   "light": 25.833328247,
   "move_type": "work",
   "outdoor_des": "light intensity shower rain",
   "outdoor_hum": 94,
   "outdoor_press": 101.7,
   "outdoor_temp": 20.04000000000002,
   "press": 101.700004578,
   "set_fanspeed": 3,
   "set_temp": 24,
   "stepNo": 62,
   "temp": 21.5,
   "time": "2020-04-22 23:47:49.406855"
  },
  {
   "body": 33.487499237,
   "feedback": "acceptable",
   "hum": 68.599998474,
   "light": 26.666671753,
   "move_type": "work",
   "outdoor_des": "light intensity shower rain",
   "outdoor_hum": 94,
   "outdoor_press": 101.7,
   "outdoor_temp": 20.05000000000001,
   "press": 101.700004578,
   "set_fanspeed": 3,
   "set_temp": 24,
   "stepNo": 63,
   "temp": 21.800001144,
   "time": "2020-04-22 23:48:27.201026"
  },
  {
   "body": 33.541667938,
   "feedback": "acceptable",
   "hum": 72.200004578,
   "light": 27.5,
   "move_type": "work",
   "outdoor_des": "light intensity shower rain",
   "outdoor_hum": 94,
   "outdoor_press": 101.7,
   "outdoor_temp": 20.04000000000002,
   "press": 101.700004578,
   "set_fanspeed": 3,
   "set_temp": 24,
   "stepNo": 64,
   "temp": 22,
   "time": "2020-04-22 23:49:04.318588"
  },
  {
   "body": 33.65625,
   "feedback": "Comfy",
   "hum": 73.5,
   "light": 28.333330154,
   "move_type": "work",
   "outdoor_des": "light intensity shower rain",
   "outdoor_hum": 94,
   "outdoor_press": 101.7,
   "outdoor_temp": 20.04000000000002,
   "press": 101.700004578,
   "set_fanspeed": 3,
   "set_temp": 24,
   "stepNo": 65,
   "temp": 22.100000381,
   "time": "2020-04-22 23:49:39.623108"
  },
  {
   "body": 33.6875,
   "feedback": "acceptable",
   "hum": 75.400001526,
   "light": 27.5,
   "move_type": "work",
   "outdoor_des": "light intensity shower rain",
   "outdoor_hum": 94,
   "outdoor_press": 101.7,
   "outdoor_temp": 20.04000000000002,
   "press": 101.700004578,
   "set_fanspeed": 3,
   "set_temp": 24,
   "stepNo": 66,
   "temp": 22.300001144,
   "time": "2020-04-22 23:50:14.812785"
  },
  {
   "body": 33.760417938,
   "feedback": "acceptable",
   "hum": 76.800003052,
   "light": 27.5,
   "move_type": "work",
   "outdoor_des": "light intensity shower rain",
   "outdoor_hum": 94,
   "outdoor_press": 101.7,
   "outdoor_temp": 20.05000000000001,
   "press": 101.700004578,
   "set_fanspeed": 3,
   "set_temp": 24,
   "stepNo": 67,
   "temp": 22.5,
   "time": "2020-04-22 23:50:50.558391"
  },
  {
   "body": 33.802082062,
   "feedback": "Comfy",
   "hum": 77.900001526,
   "light": 27.5,
   "move_type": "work",
   "outdoor_des": "light intensity shower rain",
   "outdoor_hum": 94,
   "outdoor_press": 101.7,
   "outdoor_temp": 20.04000000000002,
   "press": 101.700004578,
   "set_fanspeed": 3,
   "set_temp": 24,
   "stepNo": 68,
   "temp": 22.600000381,
   "time": "2020-04-22 23:51:27.396929"
  },
  {
   "body": 33.825000763,
   "feedback": "acceptable",
   "hum": 79,
   "light": 27.5,
   "move_type": "work",
   "outdoor_des": "light intensity shower rain",
   "outdoor_hum": 94,
   "outdoor_press": 101.7,
   "outdoor_temp": 20.04000000000002,
   "press": 101.599998474,
   "set_fanspeed": 3,
   "set_temp": 24,
   "stepNo": 69,
   "temp": 22.700000763,
   "time": "2020-04-22 23:52:05.076973"
  },
  {
   "body": 33.857143402,
   "feedback": "acceptable",
   "hum": 79.900001526,
   "light": 28.333330154,
   "move_type": "work",
   "outdoor_des": "light intensity shower rain",
   "outdoor_hum": 94,
   "outdoor_press": 101.7,
   "outdoor_temp": 20.04000000000002,
   "press": 101.599998474,
   "set_fanspeed": 3,
   "set_temp": 18,
   "stepNo": 70,
   "temp": 22.800001144,
   "time": "2020-04-22 23:52:40.847457"
  },
  {
   "body": 33.875,
   "feedback": "acceptable",
   "hum": 75.800003052,
   "light": 27.5,
   "move_type": "work",
   "outdoor_des": "light intensity shower rain",
   "outdoor_hum": 94,
   "outdoor_press": 101.7,
   "outdoor_temp": 20.04000000000002,
   "press": 101.599998474,
   "set_fanspeed": 3,
   "set_temp": 18,
   "stepNo": 71,
   "temp": 22.800001144,
   "time": "2020-04-22 23:53:28.169766"
  },
  {
   "body": 33.875,
   "feedback": "Comfy",
   "hum": 70.800003052,
   "light": 26.666671753,
   "move_type": "work",
   "outdoor_des": "light intensity shower rain",
   "outdoor_hum": 94,
   "outdoor_press": 101.7,
   "outdoor_temp": 20.04000000000002,
   "press": 101.599998474,
   "set_fanspeed": 3,
   "set_temp": 18,
   "stepNo": 72,
   "temp": 22.5,
   "time": "2020-04-22 23:54:05.098008"
  },
  {
   "body": 33.875,
   "feedback": "A Bit Cold",
   "hum": 67,
   "light": 25.833328247,
   "move_type": "work",
   "outdoor_des": "light intensity shower rain",
   "outdoor_hum": 94,
   "outdoor_press": 101.7,
   "outdoor_temp": 20.04000000000002,
   "press": 101.599998474,
   "set_fanspeed": 3,
   "set_temp": 18,
   "stepNo": 73,
   "temp": 22.300001144,
   "time": "2020-04-22 23:54:41.598566"
  },
  {
   "body": 33.84375,
   "feedback": "acceptable",
   "hum": 63.799999237,
   "light": 25.833328247,
   "move_type": "work",
   "outdoor_des": "light intensity shower rain",
   "outdoor_hum": 94,
   "outdoor_press": 101.7,
   "outdoor_temp": 20.04000000000002,
   "press": 101.599998474,
   "set_fanspeed": 3,
   "set_temp": 18,
   "stepNo": 74,
   "temp": 21.899999619,
   "time": "2020-04-22 23:55:17.559149"
  },
  {
   "body": 33.787498474,
   "feedback": "acceptable",
   "hum": 62,
   "light": 25.833328247,
   "move_type": "work",
   "outdoor_des": "light intensity shower rain",
   "outdoor_hum": 94,
   "outdoor_press": 101.7,
   "outdoor_temp": 20.04000000000002,
   "press": 101.599998474,
   "set_fanspeed": 3,
   "set_temp": 18,
   "stepNo": 75,
   "temp": 21.700000763,
   "time": "2020-04-22 23:55:52.714008"
  },
  {
   "body": 33.708332062,
   "feedback": "Cold",
   "hum": 59.900001526,
   "light": 26.666671753,
   "move_type": "work",
   "outdoor_des": "light intensity shower rain",
   "outdoor_hum": 94,
   "outdoor_press": 101.7,
   "outdoor_temp": 20.04000000000002,
   "press": 101.599998474,
   "set_fanspeed": 3,
   "set_temp": 18,
   "stepNo": 76,
   "temp": 21.399999619,
   "time": "2020-04-22 23:56:28.925155"
  },
  {
   "body": 33.65625,
   "feedback": "acceptable",
   "hum": 58.5,
   "light": 27.5,
   "move_type": "work",
   "outdoor_des": "light intensity shower rain",
   "outdoor_hum": 94,
   "outdoor_press": 101.7,
   "outdoor_temp": 20.05000000000001,
   "press": 101.599998474,
   "set_fanspeed": 3,
   "set_temp": 18,
   "stepNo": 77,
   "temp": 21.200000763,
   "time": "2020-04-22 23:57:06.044295"
  },
  {
   "body": 33.599998474,
   "feedback": "Cold",
   "hum": 57.900001526,
   "light": 27.5,
   "move_type": "work",
   "outdoor_des": "scattered clouds",
   "outdoor_hum": 88,
   "outdoor_press": 101.6,
   "outdoor_temp": 20.25,
   "press": 101.599998474,
   "set_fanspeed": 3,
   "set_temp": 18,
   "stepNo": 78,
   "temp": 21,
   "time": "2020-04-22 23:57:40.202171"
  },
  {
   "body": 33.510417938,
   "feedback": "acceptable",
   "hum": 56.900001526,
   "light": 27.5,
   "move_type": "work",
   "outdoor_des": "scattered clouds",
   "outdoor_hum": 88,
   "outdoor_press": 101.6,
   "outdoor_temp": 20.25,
   "press": 101.599998474,
   "set_fanspeed": 3,
   "set_temp": 18,
   "stepNo": 79,
   "temp": 20.800001144,
   "time": "2020-04-22 23:58:15.455165"
  },
  {
   "body": 33.424999237,
   "feedback": "Cold",
   "hum": 56.400001526,
   "light": 27.5,
   "move_type": "work",
   "outdoor_des": "scattered clouds",
   "outdoor_hum": 88,
   "outdoor_press": 101.6,
   "outdoor_temp": 20.25,
   "press": 101.599998474,
   "set_fanspeed": 1,
   "set_temp": 24,
   "stepNo": 80,
   "temp": 20.700000763,
   "time": "2020-04-22 23:58:53.406574"
  },
  {
   "body": 33.34375,
   "feedback": "A Bit Cold",
   "hum": 58.299999237,
   "light": 26.666671753,
   "move_type": "work",
   "outdoor_des": "scattered clouds",
   "outdoor_hum": 88,
   "outdoor_press": 101.6,
   "outdoor_temp": 20.25,
   "press": 101.599998474,
   "set_fanspeed": 1,
   "set_temp": 24,
   "stepNo": 81,
   "temp": 20.5,
   "time": "2020-04-22 23:59:37.242573"
  },
  {
   "body": 33.25,
   "feedback": "acceptable",
   "hum": 64.400001526,
   "light": 26.666671753,
   "move_type": "work",
   "outdoor_des": "scattered clouds",
   "outdoor_hum": 88,
   "outdoor_press": 101.6,
   "outdoor_temp": 20.260000000000048,
   "press": 101.599998474,
   "set_fanspeed": 1,
   "set_temp": 24,
   "stepNo": 82,
   "temp": 20.800001144,
   "time": "2020-04-23 00:00:14.379573"
  },
  {
   "body": 33.197917938,
   "feedback": "acceptable",
   "hum": 67.900001526,
   "light": 26.666671753,
   "move_type": "work",
   "outdoor_des": "scattered clouds",
   "outdoor_hum": 88,
   "outdoor_press": 101.6,
   "outdoor_temp": 20.25,
   "press": 101.599998474,
   "set_fanspeed": 1,
   "set_temp": 24,
   "stepNo": 83,
   "temp": 21,
   "time": "2020-04-23 00:00:51.797715"
  },
  {
   "body": 33.25,
   "feedback": "acceptable",
   "hum": 70.900001526,
   "light": 26.666671753,
   "move_type": "work",
   "outdoor_des": "scattered clouds",
   "outdoor_hum": 88,
   "outdoor_press": 101.6,
   "outdoor_temp": 20.25,
   "press": 101.599998474,
   "set_fanspeed": 1,
   "set_temp": 24,
   "stepNo": 84,
   "temp": 21.300001144,
   "time": "2020-04-23 00:01:29.224203"
  },
  {
   "body": 33.25,
   "feedback": "Comfy",
   "hum": 72.900001526,
   "light": 26.666671753,
   "move_type": "work",
   "outdoor_des": "scattered clouds",
   "outdoor_hum": 88,
   "outdoor_press": 101.6,
   "outdoor_temp": 20.25,
   "press": 101.599998474,
   "set_fanspeed": 1,
   "set_temp": 24,
   "stepNo": 85,
   "temp": 21.5,
   "time": "2020-04-23 00:02:08.346072"
  },
  {
   "body": 33.3125,
   "feedback": "acceptable",
   "hum": 74,
   "light": 26.666671753,
   "move_type": "work",
   "outdoor_des": "scattered clouds",
   "outdoor_hum": 88,
   "outdoor_press": 101.6,
   "outdoor_temp": 20.25,
   "press": 101.5,
   "set_fanspeed": 1,
   "set_temp": 24,
   "stepNo": 86,
   "temp": 21.700000763,
   "time": "2020-04-23 00:02:45.125860"
  },
  {
   "body": 33.3125,
   "feedback": "acceptable",
   "hum": 75.200004578,
   "light": 26.666671753,
   "move_type": "work",
   "outdoor_des": "scattered clouds",
   "outdoor_hum": 88,
   "outdoor_press": 101.6,
   "outdoor_temp": 20.260000000000048,
   "press": 101.5,
   "set_fanspeed": 1,
   "set_temp": 24,
   "stepNo": 87,
   "temp": 21.899999619,
   "time": "2020-04-23 00:03:20.983475"
  },
  {
   "body": 33.3125,
   "feedback": "acceptable",
   "hum": 77,
   "light": 26.666671753,
   "move_type": "work",
   "outdoor_des": "scattered clouds",
   "outdoor_hum": 88,
   "outdoor_press": 101.6,
   "outdoor_temp": 20.25,
   "press": 101.5,
   "set_fanspeed": 1,
   "set_temp": 24,
   "stepNo": 88,
   "temp": 22.100000381,
   "time": "2020-04-23 00:03:57.864873"
  },
  {
   "body": 33.333332062,
   "feedback": "acceptable",
   "hum": 77.800003052,
   "light": 26.666671753,
   "move_type": "work",
   "outdoor_des": "scattered clouds",
   "outdoor_hum": 88,
   "outdoor_press": 101.6,
   "outdoor_temp": 20.25,
   "press": 101.5,
   "set_fanspeed": 1,
   "set_temp": 24,
   "stepNo": 89,
   "temp": 22.200000763,
   "time": "2020-04-23 00:04:34.403887"
  },
  {
   "body": 33.375,
   "feedback": "acceptable",
   "hum": 78.5,
   "light": 27.5,
   "move_type": "work",
   "outdoor_des": "scattered clouds",
   "outdoor_hum": 88,
   "outdoor_press": 101.6,
   "outdoor_temp": 20.25,
   "press": 101.5,
   "set_fanspeed": 2,
   "set_temp": 18,
   "stepNo": 90,
   "temp": 22.300001144,
   "time": "2020-04-23 00:05:11.166038"
  },
  {
   "body": 33.390625,
   "feedback": "acceptable",
   "hum": 75.400001526,
   "light": 26.666671753,
   "move_type": "work",
   "outdoor_des": "scattered clouds",
   "outdoor_hum": 88,
   "outdoor_press": 101.6,
   "outdoor_temp": 20.25,
   "press": 101.5,
   "set_fanspeed": 2,
   "set_temp": 18,
   "stepNo": 91,
   "temp": 22.399999619,
   "time": "2020-04-23 00:05:56.186492"
  },
  {
   "body": 33.4375,
   "feedback": "A Bit Cold",
   "hum": 69.900001526,
   "light": 26.666671753,
   "move_type": "work",
   "outdoor_des": "scattered clouds",
   "outdoor_hum": 88,
   "outdoor_press": 101.6,
   "outdoor_temp": 20.260000000000048,
   "press": 101.5,
   "set_fanspeed": 2,
   "set_temp": 18,
   "stepNo": 92,
   "temp": 22.200000763,
   "time": "2020-04-23 00:06:34.633993"
  },
  {
   "body": 33.385417938,
   "feedback": "acceptable",
   "hum": 65.300003052,
   "light": 27.5,
   "move_type": "work",
   "outdoor_des": "scattered clouds",
   "outdoor_hum": 88,
   "outdoor_press": 101.6,
   "outdoor_temp": 20.25,
   "press": 101.5,
   "set_fanspeed": 2,
   "set_temp": 18,
   "stepNo": 93,
   "temp": 21.899999619,
   "time": "2020-04-23 00:07:11.660859"
  },
  {
   "body": 33.364582062,
   "feedback": "Cold",
   "hum": 62.799999237,
   "light": 27.5,
   "move_type": "work",
   "outdoor_des": "scattered clouds",
   "outdoor_hum": 88,
   "outdoor_press": 101.6,
   "outdoor_temp": 20.25,
   "press": 101.5,
   "set_fanspeed": 2,
   "set_temp": 18,
   "stepNo": 94,
   "temp": 21.700000763,
   "time": "2020-04-23 00:07:48.749881"
  },
  {
   "body": 33.302082062,
   "feedback": "Cold",
   "hum": 60,
   "light": 27.5,
   "move_type": "work",
   "outdoor_des": "scattered clouds",
   "outdoor_hum": 88,
   "outdoor_press": 101.6,
   "outdoor_temp": 20.25,
   "press": 101.5,
   "set_fanspeed": 2,
   "set_temp": 18,
   "stepNo": 95,
   "temp": 21.5,
   "time": "2020-04-23 00:08:27.861211"
  },
  {
   "body": 33.25,
   "feedback": "acceptable",
   "hum": 58.100002289,
   "light": 27.5,
   "move_type": "work",
   "outdoor_des": "scattered clouds",
   "outdoor_hum": 88,
   "outdoor_press": 101.6,
   "outdoor_temp": 20.25,
   "press": 101.5,
   "set_fanspeed": 2,
   "set_temp": 18,
   "stepNo": 96,
   "temp": 21.399999619,
   "time": "2020-04-23 00:09:03.958531"
  },
  {
   "body": 33.1875,
   "feedback": "acceptable",
   "hum": 56.700000763,
   "light": 27.5,
   "move_type": "work",
   "outdoor_des": "scattered clouds",
   "outdoor_hum": 88,
   "outdoor_press": 101.6,
   "outdoor_temp": 20.25,
   "press": 101.5,
   "set_fanspeed": 2,
   "set_temp": 18,
   "stepNo": 97,
   "temp": 21.300001144,
   "time": "2020-04-23 00:09:39.001291"
  },
  {
   "body": 33.099998474,
   "feedback": "Cold",
   "hum": 55.600002289,
   "light": 27.5,
   "move_type": "work",
   "outdoor_des": "scattered clouds",
   "outdoor_hum": 88,
   "outdoor_press": 101.6,
   "outdoor_temp": 20.25,
   "press": 101.5,
   "set_fanspeed": 2,
   "set_temp": 18,
   "stepNo": 98,
   "temp": 21.100000381,
   "time": "2020-04-23 00:10:15.318152"
  },
  {
   "body": 33.010417938,
   "feedback": "acceptable",
   "hum": 54.5,
   "light": 27.5,
   "move_type": "work",
   "outdoor_des": "scattered clouds",
   "outdoor_hum": 88,
   "outdoor_press": 101.6,
   "outdoor_temp": 20.25,
   "press": 101.5,
   "set_fanspeed": 2,
   "set_temp": 18,
   "stepNo": 99,
   "temp": 21,
   "time": "2020-04-23 00:10:51.167877"
  },
  {
   "body": 32.912498474,
   "feedback": "acceptable",
   "hum": 53.700000763,
   "light": 27.5,
   "move_type": "work",
   "outdoor_des": "scattered clouds",
   "outdoor_hum": 88,
   "outdoor_press": 101.6,
   "outdoor_temp": 20.25,
   "press": 101.5,
   "set_fanspeed": 2,
   "set_temp": 24,
   "stepNo": 100,
   "temp": 21,
   "time": "2020-04-23 00:11:28.054778"
  },
  {
   "body": 32.857143402,
   "feedback": "Cold",
   "hum": 56.400001526,
   "light": 27.5,
   "move_type": "work",
   "outdoor_des": "scattered clouds",
   "outdoor_hum": 88,
   "outdoor_press": 101.6,
   "outdoor_temp": 20.25,
   "press": 101.5,
   "set_fanspeed": 2,
   "set_temp": 24,
   "stepNo": 101,
   "temp": 20.800001144,
   "time": "2020-04-23 00:12:09.227044"
  },
  {
   "body": 32.8125,
   "feedback": "acceptable",
   "hum": 62.900001526,
   "light": 26.666671753,
   "move_type": "work",
   "outdoor_des": "scattered clouds",
   "outdoor_hum": 88,
   "outdoor_press": 101.6,
   "outdoor_temp": 20.07000000000005,
   "press": 101.5,
   "set_fanspeed": 2,
   "set_temp": 24,
   "stepNo": 102,
   "temp": 20.800001144,
   "time": "2020-04-23 00:12:44.623401"
  },
  {
   "body": 32.8125,
   "feedback": "acceptable",
   "hum": 67.200004578,
   "light": 27.5,
   "move_type": "work",
   "outdoor_des": "scattered clouds",
   "outdoor_hum": 88,
   "outdoor_press": 101.6,
   "outdoor_temp": 20.07000000000005,
   "press": 101.5,
   "set_fanspeed": 2,
   "set_temp": 24,
   "stepNo": 103,
   "temp": 20.800001144,
   "time": "2020-04-23 00:13:22.094091"
  },
  {
   "body": 32.760417938,
   "feedback": "acceptable",
   "hum": 70.099998474,
   "light": 27.5,
   "move_type": "work",
   "outdoor_des": "scattered clouds",
   "outdoor_hum": 88,
   "outdoor_press": 101.6,
   "outdoor_temp": 20.25,
   "press": 101.5,
   "set_fanspeed": 2,
   "set_temp": 24,
   "stepNo": 104,
   "temp": 21,
   "time": "2020-04-23 00:13:58.326922"
  },
  {
   "body": 32.762500763,
   "feedback": "acceptable",
   "hum": 72.599998474,
   "light": 27.5,
   "move_type": "work",
   "outdoor_des": "scattered clouds",
   "outdoor_hum": 88,
   "outdoor_press": 101.6,
   "outdoor_temp": 20.25,
   "press": 101.5,
   "set_fanspeed": 2,
   "set_temp": 24,
   "stepNo": 105,
   "temp": 21.200000763,
   "time": "2020-04-23 00:14:35.245855"
  },
  {
   "body": 32.8125,
   "feedback": "A Bit Cold",
   "hum": 74.300003052,
   "light": 27.5,
   "move_type": "work",
   "outdoor_des": "scattered clouds",
   "outdoor_hum": 88,
   "outdoor_press": 101.6,
   "outdoor_temp": 20.25,
   "press": 101.5,
   "set_fanspeed": 2,
   "set_temp": 24,
   "stepNo": 106,
   "temp": 21.399999619,
   "time": "2020-04-23 00:15:10.244825"
  },
  {
   "body": 32.8125,
   "feedback": "acceptable",
   "hum": 75.700004578,
   "light": 26.666671753,
   "move_type": "work",
   "outdoor_des": "scattered clouds",
   "outdoor_hum": 88,
   "outdoor_press": 101.6,
   "outdoor_temp": 20.25,
   "press": 101.5,
   "set_fanspeed": 2,
   "set_temp": 24,
   "stepNo": 107,
   "temp": 21.600000381,
   "time": "2020-04-23 00:15:47.742508"
  },
  {
   "body": 32.825000763,
   "feedback": "acceptable",
   "hum": 76.300003052,
   "light": 27.5,
   "move_type": "work",
   "outdoor_des": "scattered clouds",
   "outdoor_hum": 88,
   "outdoor_press": 101.6,
   "outdoor_temp": 20.25,
   "press": 101.5,
   "set_fanspeed": 2,
   "set_temp": 24,
   "stepNo": 108,
   "temp": 21.800001144,
   "time": "2020-04-23 00:16:22.385368"
  },
  {
   "body": 32.875,
   "feedback": "acceptable",
   "hum": 78.099998474,
   "light": 27.5,
   "move_type": "work",
   "outdoor_des": "scattered clouds",
   "outdoor_hum": 88,
   "outdoor_press": 101.6,
   "outdoor_temp": 20.25,
   "press": 101.5,
   "set_fanspeed": 2,
   "set_temp": 24,
   "stepNo": 109,
   "temp": 21.899999619,
   "time": "2020-04-23 00:16:59.163360"
  },
  {
   "body": 32.950000763,
   "feedback": "acceptable",
   "hum": 79.200004578,
   "light": 27.5,
   "move_type": "work",
   "outdoor_des": "scattered clouds",
   "outdoor_hum": 88,
   "outdoor_press": 101.6,
   "outdoor_temp": 20.25,
   "press": 101.5,
   "set_fanspeed": 3,
   "set_temp": 18,
   "stepNo": 110,
   "temp": 22,
   "time": "2020-04-23 00:17:35.855969"
  },
  {
   "body": 33.008930206,
   "feedback": "acceptable",
   "hum": 75.800003052,
   "light": 27.5,
   "move_type": "work",
   "outdoor_des": "scattered clouds",
   "outdoor_hum": 88,
   "outdoor_press": 101.6,
   "outdoor_temp": 20.07000000000005,
   "press": 101.5,
   "set_fanspeed": 3,
   "set_temp": 18,
   "stepNo": 111,
   "temp": 22,
   "time": "2020-04-23 00:18:19.134045"
  },
  {
   "body": 33.09375,
   "feedback": "acceptable",
   "hum": 70.800003052,
   "light": 26.666671753,
   "move_type": "work",
   "outdoor_des": "scattered clouds",
   "outdoor_hum": 88,
   "outdoor_press": 101.6,
   "outdoor_temp": 20.07000000000005,
   "press": 101.5,
   "set_fanspeed": 3,
   "set_temp": 18,
   "stepNo": 112,
   "temp": 21.899999619,
   "time": "2020-04-23 00:18:56.197732"
  },
  {
   "body": 33.125,
   "feedback": "acceptable",
   "hum": 66.800003052,
   "light": 26.666671753,
   "move_type": "work",
   "outdoor_des": "scattered clouds",
   "outdoor_hum": 88,
   "outdoor_press": 101.6,
   "outdoor_temp": 20.07000000000005,
   "press": 101.5,
   "set_fanspeed": 3,
   "set_temp": 18,
   "stepNo": 113,
   "temp": 21.600000381,
   "time": "2020-04-23 00:19:30.941740"
  },
  {
   "body": 33.112499237,
   "feedback": "A Bit Cold",
   "hum": 64,
   "light": 26.666671753,
   "move_type": "work",
   "outdoor_des": "scattered clouds",
   "outdoor_hum": 88,
   "outdoor_press": 101.6,
   "outdoor_temp": 20.07000000000005,
   "press": 101.5,
   "set_fanspeed": 3,
   "set_temp": 18,
   "stepNo": 114,
   "temp": 21.300001144,
   "time": "2020-04-23 00:20:08.505837"
  },
  {
   "body": 33.010417938,
   "feedback": "Cold",
   "hum": 61.700000763,
   "light": 26.666671753,
   "move_type": "work",
   "outdoor_des": "scattered clouds",
   "outdoor_hum": 88,
   "outdoor_press": 101.6,
   "outdoor_temp": 20.07000000000005,
   "press": 101.5,
   "set_fanspeed": 3,
   "set_temp": 18,
   "stepNo": 115,
   "temp": 21,
   "time": "2020-04-23 00:20:43.547215"
  },
  {
   "body": 32.989582062,
   "feedback": "acceptable",
   "hum": 60,
   "light": 27.5,
   "move_type": "work",
   "outdoor_des": "scattered clouds",
   "outdoor_hum": 88,
   "outdoor_press": 101.6,
   "outdoor_temp": 20.07000000000005,
   "press": 101.5,
   "set_fanspeed": 3,
   "set_temp": 18,
   "stepNo": 116,
   "temp": 20.800001144,
   "time": "2020-04-23 00:21:19.969880"
  },
  {
   "body": 32.822917938,
   "feedback": "acceptable",
   "hum": 58.200000763,
   "light": 27.5,
   "move_type": "work",
   "outdoor_des": "scattered clouds",
   "outdoor_hum": 88,
   "outdoor_press": 101.6,
   "outdoor_temp": 20.07000000000005,
   "press": 101.5,
   "set_fanspeed": 3,
   "set_temp": 18,
   "stepNo": 117,
   "temp": 20.600000381,
   "time": "2020-04-23 00:21:59.014604"
  },
  {
   "body": 32.729167938,
   "feedback": "acceptable",
   "hum": 57.400001526,
   "light": 27.5,
   "move_type": "work",
   "outdoor_des": "scattered clouds",
   "outdoor_hum": 88,
   "outdoor_press": 101.6,
   "outdoor_temp": 20.07000000000005,
   "press": 101.5,
   "set_fanspeed": 3,
   "set_temp": 18,
   "stepNo": 118,
   "temp": 20.399999619,
   "time": "2020-04-23 00:22:33.697868"
  },
  {
   "body": 32.662498474,
   "feedback": "acceptable",
   "hum": 56.299999237,
   "light": 27.5,
   "move_type": "work",
   "outdoor_des": "scattered clouds",
   "outdoor_hum": 88,
   "outdoor_press": 101.6,
   "outdoor_temp": 20.07000000000005,
   "press": 101.5,
   "set_fanspeed": 3,
   "set_temp": 18,
   "stepNo": 119,
   "temp": 20.200000763,
   "time": "2020-04-23 00:23:11.827657"
  },
  {
   "body": 32.614582062,
   "feedback": "acceptable",
   "hum": 55.900001526,
   "light": 27.5,
   "move_type": "work",
   "outdoor_des": "scattered clouds",
   "outdoor_hum": 88,
   "outdoor_press": 101.6,
   "outdoor_temp": 20.07000000000005,
   "press": 101.5,
   "set_fanspeed": 2,
   "set_temp": 24,
   "stepNo": 120,
   "temp": 20,
   "time": "2020-04-23 00:23:47.946163"
  },
  {
   "body": 32.526786804,
   "feedback": "A Bit Cold",
   "hum": 59.200000763,
   "light": 27.5,
   "move_type": "work",
   "outdoor_des": "scattered clouds",
   "outdoor_hum": 88,
   "outdoor_press": 101.6,
   "outdoor_temp": 20.07000000000005,
   "press": 101.5,
   "set_fanspeed": 2,
   "set_temp": 24,
   "stepNo": 121,
   "temp": 19.800001144,
   "time": "2020-04-23 00:24:33.012290"
  },
  {
   "body": 32.40625,
   "feedback": "acceptable",
   "hum": 65.200004578,
   "light": 26.666671753,
   "move_type": "work",
   "outdoor_des": "scattered clouds",
   "outdoor_hum": 88,
   "outdoor_press": 101.6,
   "outdoor_temp": 20.07000000000005,
   "press": 101.5,
   "set_fanspeed": 2,
   "set_temp": 24,
   "stepNo": 122,
   "temp": 20,
   "time": "2020-04-23 00:25:09.317892"
  },
  {
   "body": 32.375,
   "feedback": "acceptable",
   "hum": 69.099998474,
   "light": 26.666671753,
   "move_type": "work",
   "outdoor_des": "scattered clouds",
   "outdoor_hum": 88,
   "outdoor_press": 101.6,
   "outdoor_temp": 20.07000000000005,
   "press": 101.5,
   "set_fanspeed": 2,
   "set_temp": 24,
   "stepNo": 123,
   "temp": 20.300001144,
   "time": "2020-04-23 00:25:45.317874"
  },
  {
   "body": 32.375,
   "feedback": "acceptable",
   "hum": 71.5,
   "light": 27.5,
   "move_type": "work",
   "outdoor_des": "scattered clouds",
   "outdoor_hum": 88,
   "outdoor_press": 101.6,
   "outdoor_temp": 20.07000000000005,
   "press": 101.5,
   "set_fanspeed": 2,
   "set_temp": 24,
   "stepNo": 124,
   "temp": 20.5,
   "time": "2020-04-23 00:26:22.759812"
  },
  {
   "body": 32.40625,
   "feedback": "A Bit Cold",
   "hum": 73.900001526,
   "light": 26.666671753,
   "move_type": "work",
   "outdoor_des": "scattered clouds",
   "outdoor_hum": 88,
   "outdoor_press": 101.6,
   "outdoor_temp": 20.07000000000005,
   "press": 101.5,
   "set_fanspeed": 2,
   "set_temp": 24,
   "stepNo": 125,
   "temp": 20.800001144,
   "time": "2020-04-23 00:27:00.001008"
  },
  {
   "body": 32.4375,
   "feedback": "acceptable",
   "hum": 75.200004578,
   "light": 27.5,
   "move_type": "work",
   "outdoor_des": "scattered clouds",
   "outdoor_hum": 88,
   "outdoor_press": 101.6,
   "outdoor_temp": 20.07000000000005,
   "press": 101.5,
   "set_fanspeed": 2,
   "set_temp": 24,
   "stepNo": 126,
   "temp": 21,
   "time": "2020-04-23 00:27:35.184756"
  },
  {
   "body": 32.462501526,
   "feedback": "acceptable",
   "hum": 76.900001526,
   "light": 27.5,
   "move_type": "work",
   "outdoor_des": "scattered clouds",
   "outdoor_hum": 88,
   "outdoor_press": 101.6,
   "outdoor_temp": 20.07000000000005,
   "press": 101.5,
   "set_fanspeed": 2,
   "set_temp": 24,
   "stepNo": 127,
   "temp": 21.200000763,
   "time": "2020-04-23 00:28:12.714878"
  },
  {
   "body": 32.508930206,
   "feedback": "acceptable",
   "hum": 77.800003052,
   "light": 27.5,
   "move_type": "work",
   "outdoor_des": "scattered clouds",
   "outdoor_hum": 88,
   "outdoor_press": 101.6,
   "outdoor_temp": 20.07000000000005,
   "press": 101.5,
   "set_fanspeed": 2,
   "set_temp": 24,
   "stepNo": 128,
   "temp": 21.399999619,
   "time": "2020-04-23 00:28:47.629820"
  },
  {
   "body": 32.5625,
   "feedback": "Comfy",
   "hum": 79.300003052,
   "light": 28.333330154,
   "move_type": "work",
   "outdoor_des": "scattered clouds",
   "outdoor_hum": 94,
   "outdoor_press": 101.4,
   "outdoor_temp": 19.870000000000005,
   "press": 101.5,
   "set_fanspeed": 2,
   "set_temp": 24,
   "stepNo": 129,
   "temp": 21.5,
   "time": "2020-04-23 00:29:24.189755"
  },
  {
   "body": 32.572917938,
   "feedback": "acceptable",
   "hum": 79.700004578,
   "light": 27.5,
   "move_type": "work",
   "outdoor_des": "scattered clouds",
   "outdoor_hum": 94,
   "outdoor_press": 101.4,
   "outdoor_temp": 19.870000000000005,
   "press": 101.5,
   "set_fanspeed": 3,
   "set_temp": 18,
   "stepNo": 130,
   "temp": 21.600000381,
   "time": "2020-04-23 00:30:01.754782"
  },
  {
   "body": 32.625,
   "feedback": "acceptable",
   "hum": 76.300003052,
   "light": 28.333330154,
   "move_type": "work",
   "outdoor_des": "scattered clouds",
   "outdoor_hum": 94,
   "outdoor_press": 101.4,
   "outdoor_temp": 19.870000000000005,
   "press": 101.5,
   "set_fanspeed": 3,
   "set_temp": 18,
   "stepNo": 131,
   "temp": 21.700000763,
   "time": "2020-04-23 00:30:47.163424"
  }
 ]
}