{
 "datapack": [
  {
   "body": 25.619754791,
   "feedback": "acceptable",
   "hum": 82.599998474,
   "light": 24.166669846,
   "move_type": "work",
   "outdoor_des": "broken clouds",
   "outdoor_hum": 79,
   "outdoor_press": 100.8,
   "outdoor_temp": 28.170000000000016,
   "press": 100.800003052,
   "set_fanspeed": 3,
   "set_temp": 23,
   "stepNo": 0,
   "temp": 26.700000763,
   "time": "2020-05-09 19:29:11.229677"
  },
  {
   "body": 25.943181992,
   "feedback": "acceptable",
   "hum": 75.599998474,
   "light": 25,
   "move_type": "work",
   "outdoor_des": "broken clouds",
   "outdoor_hum": 79,
   "outdoor_press": 100.8,
   "outdoor_temp": 28.170000000000016,
   "press": 100.800003052,
   "set_fanspeed": 3,
   "set_temp": 23,
   "stepNo": 1,
   "temp": 26.399999619,
   "time": "2020-05-09 19:30:24.948969"
  },
  {
   "body": 25.835227966,
   "feedback": "acceptable",
   "hum": 70,
   "light": 25.833328247,
   "move_type": "work",
   "outdoor_des": "broken clouds",
   "outdoor_hum": 79,
   "outdoor_press": 100.8,
   "outdoor_temp": 28.170000000000016,
   "press": 100.800003052,
   "set_fanspeed": 3,
   "set_temp": 23,
   "stepNo": 2,
   "temp": 26,
   "time": "2020-05-09 19:31:30.558845"
  },
  {
   "body": 25.631250381,
   "feedback": "acceptable",
   "hum": 66.099998474,
   "light": 25.833328247,
   "move_type": "work",
   "outdoor_des": "broken clouds",
   "outdoor_hum": 79,
   "outdoor_press": 100.8,
   "outdoor_temp": 28.170000000000016,
   "press": 100.800003052,
   "set_fanspeed": 3,
   "set_temp": 23,
   "stepNo": 3,
   "temp": 25.600000381,
   "time": "2020-05-09 19:32:35.709788"
  },
  {
   "body": 25.412500381,
   "feedback": "acceptable",
   "hum": 62.900001526,
   "light": 25.833328247,
   "move_type": "work",
   "outdoor_des": "broken clouds",
   "outdoor_hum": 79,
   "outdoor_press": 100.8,
   "outdoor_temp": 28.170000000000016,
   "press": 100.800003052,
   "set_fanspeed": 3,
   "set_temp": 23,
   "stepNo": 4,
   "temp": 25.100000381,
   "time": "2020-05-09 19:33:41.747794"
  },
  {
   "body": 25.168750763,
   "feedback": "acceptable",
   "hum": 61.200000763,
   "light": 25.833328247,
   "move_type": "work",
   "outdoor_des": "broken clouds",
   "outdoor_hum": 79,
   "outdoor_press": 100.8,
   "outdoor_temp": 28.170000000000016,
   "press": 100.800003052,
   "set_fanspeed": 3,
   "set_temp": 23,
   "stepNo": 5,
   "temp": 24.800001144,
   "time": "2020-05-09 19:34:47.871220"
  },
  {
   "body": 25,
   "feedback": "acceptable",
   "hum": 71.700004578,
   "light": 25,
   "move_type": "work",
   "outdoor_des": "broken clouds",
   "outdoor_hum": 79,
   "outdoor_press": 100.8,
   "outdoor_temp": 28.170000000000016,
   "press": 100.800003052,
   "set_fanspeed": 3,
   "set_temp": 23,
   "stepNo": 6,
   "temp": 24.700000763,
   "time": "2020-05-09 19:35:52.658627"
  },
  {
   "body": 24.981250763,
   "feedback": "acceptable",
   "hum": 77.599998474,
   "light": 25,
   "move_type": "work",
   "outdoor_des": "broken clouds",
   "outdoor_hum": 79,
   "outdoor_press": 100.8,
   "outdoor_temp": 28.170000000000016,
   "press": 100.800003052,
   "set_fanspeed": 3,
   "set_temp": 23,
   "stepNo": 7,
   "temp": 24.800001144,
   "time": "2020-05-09 19:36:58.174632"
  },
  {
   "body": 25.006250381,
   "feedback": "acceptable",
   "hum": 81.5,
   "light": 24.166669846,
   "move_type": "work",
   "outdoor_des": "broken clouds",
   "outdoor_hum": 79,
   "outdoor_press": 100.8,
   "outdoor_temp": 28.170000000000016,
   "press": 100.800003052,
   "set_fanspeed": 3,
   "set_temp": 23,
   "stepNo": 8,
   "temp": 25,
   "time": "2020-05-09 19:38:02.669479"
  },
  {
   "body": 25.0625,
   "feedback": "acceptable",
   "hum": 73.800003052,
   "light": 25,
   "move_type": "work",
   "outdoor_des": "broken clouds",
   "outdoor_hum": 79,
   "outdoor_press": 100.8,
   "outdoor_temp": 28.170000000000016,
   "press": 100.800003052,
   "set_fanspeed": 3,
   "set_temp": 23,
   "stepNo": 9,
   "temp": 24.899999619,
   "time": "2020-05-09 19:39:07.411362"
  },
  {
   "body": 24.965909958,
   "feedback": "acceptable",
   "hum": 67.800003052,
   "light": 25.833328247,
   "move_type": "work",
   "outdoor_des": "broken clouds",
   "outdoor_hum": 79,
   "outdoor_press": 100.8,
   "outdoor_temp": 28.170000000000016,
   "press": 100.800003052,
   "set_fanspeed": 3,
   "set_temp": 23,
   "stepNo": 10,
   "temp": 24.700000763,
   "time": "2020-05-09 19:40:12.824705"
  },
  {
   "body": 24.806249619,
   "feedback": "acceptable",
   "hum": 63.700000763,
   "light": 25.833328247,
   "move_type": "work",
   "outdoor_des": "broken clouds",
   "outdoor_hum": 74,
   "outdoor_press": 100.8,
   "outdoor_temp": 27.99000000000001,
   "press": 100.800003052,
   "set_fanspeed": 3,
   "set_temp": 23,
   "stepNo": 11,
   "temp": 24.399999619,
   "time": "2020-05-09 19:41:18.057602"
  },
  {
   "body": 24.618749619,
   "feedback": "acceptable",
   "hum": 69.300003052,
   "light": 25.833328247,
   "move_type": "work",
   "outdoor_des": "broken clouds",
   "outdoor_hum": 74,
   "outdoor_press": 100.8,
   "outdoor_temp": 27.99000000000001,
   "press": 100.800003052,
   "set_fanspeed": 3,
   "set_temp": 23,
   "stepNo": 12,
   "temp": 24.200000763,
   "time": "2020-05-09 19:42:24.638861"
  },
  {
   "body": 24.612499237,
   "feedback": "acceptable",
   "hum": 76.400001526,
   "light": 25,
   "move_type": "work",
   "outdoor_des": "broken clouds",
   "outdoor_hum": 74,
   "outdoor_press": 100.8,
   "outdoor_temp": 27.99000000000001,
   "press": 100.800003052,
   "set_fanspeed": 3,
   "set_temp": 23,
   "stepNo": 13,
   "temp": 24.300001144,
   "time": "2020-05-09 19:43:30.776403"
  },
  {
   "body": 24.664772034,
   "feedback": "acceptable",
   "hum": 80.900001526,
   "light": 24.166669846,
   "move_type": "work",
   "outdoor_des": "broken clouds",
   "outdoor_hum": 74,
   "outdoor_press": 100.8,
   "outdoor_temp": 27.99000000000001,
   "press": 100.800003052,
   "set_fanspeed": 3,
   "set_temp": 23,
   "stepNo": 14,
   "temp": 24.5,
   "time": "2020-05-09 19:44:39.293910"
  },
  {
   "body": 24.727272034,
   "feedback": "acceptable",
   "hum": 80.700004578,
   "light": 25,
   "move_type": "work",
   "outdoor_des": "broken clouds",
   "outdoor_hum": 74,
   "outdoor_press": 100.8,
   "outdoor_temp": 27.99000000000001,
   "press": 100.800003052,
   "set_fanspeed": 2,
   "set_temp": 25,
   "stepNo": 15,
   "temp": 24.600000381,
   "time": "2020-05-09 19:45:46.391805"
  },
  {
   "body": 24.744318008,
   "feedback": "acceptable",
   "hum": 81.300003052,
   "light": 25,
   "move_type": "work",
   "outdoor_des": "broken clouds",
   "outdoor_hum": 74,
   "outdoor_press": 100.8,
   "outdoor_temp": 27.99000000000001,
   "press": 100.800003052,
   "set_fanspeed": 2,
   "set_temp": 25,
   "stepNo": 16,
   "temp": 24.700000763,
   "time": "2020-05-09 19:46:56.631381"
  },
  {
   "body": 24.787500381,
   "feedback": "acceptable",
   "hum": 84.5,
   "light": 25,
   "move_type": "work",
   "outdoor_des": "broken clouds",
   "outdoor_hum": 74,
   "outdoor_press": 100.8,
   "outdoor_temp": 27.99000000000001,
   "press": 100.800003052,
   "set_fanspeed": 2,
   "set_temp": 25,
   "stepNo": 17,
   "temp": 24.800001144,
   "time": "2020-05-09 19:48:02.905076"
  },
  {
   "body": 24.846590042,
   "feedback": "acceptable",
   "hum": 85.900001526,
   "light": 25,
   "move_type": "work",
   "outdoor_des": "broken clouds",
   "outdoor_hum": 74,
   "outdoor_press": 100.8,
   "outdoor_temp": 27.99000000000001,
   "press": 100.800003052,
   "set_fanspeed": 2,
   "set_temp": 25,
   "stepNo": 18,
   "temp": 25,
   "time": "2020-05-09 19:49:09.551711"
  },
  {
   "body": 24.90625,
   "feedback": "acceptable",
   "hum": 87.800003052,
   "light": 25,
   "move_type": "work",
   "outdoor_des": "broken clouds",
   "outdoor_hum": 74,
   "outdoor_press": 100.8,
   "outdoor_temp": 27.99000000000001,
   "press": 100.800003052,
   "set_fanspeed": 2,
   "set_temp": 25,
   "stepNo": 19,
   "temp": 25.100000381,
   "time": "2020-05-09 19:50:15.602659"
  },
  {
   "body": 24.962499619,
   "feedback": "acceptable",
   "hum": 88.700004578,
   "light": 25,
   "move_type": "work",
   "outdoor_des": "broken clouds",
   "outdoor_hum": 74,
   "outdoor_press": 100.8,
   "outdoor_temp": 27.99000000000001,
   "press": 100.800003052,
   "set_fanspeed": 2,
   "set_temp": 25,
   "stepNo": 20,
   "temp": 25.300001144,
   "time": "2020-05-09 19:51:22.257155"
  },
  {
   "body": 25.034090042,
   "feedback": "acceptable",
   "hum": 89.599998474,
   "light": 24.166669846,
   "move_type": "work",
   "outdoor_des": "broken clouds",
   "outdoor_hum": 74,
   "outdoor_press": 100.8,
   "outdoor_temp": 27.99000000000001,
   "press": 100.800003052,
   "set_fanspeed": 2,
   "set_temp": 25,
   "stepNo": 21,
   "temp": 25.399999619,
   "time": "2020-05-09 19:52:28.462410"
  },
  {
   "body": 25.100000381,
   "feedback": "acceptable",
   "hum": 90.099998474,
   "light": 25,
   "move_type": "work",
   "outdoor_des": "broken clouds",
   "outdoor_hum": 74,
   "outdoor_press": 100.8,
   "outdoor_temp": 27.99000000000001,
   "press": 100.800003052,
   "set_fanspeed": 2,
   "set_temp": 25,
   "stepNo": 22,
   "temp": 25.5,
   "time": "2020-05-09 19:53:32.938266"
  },
  {
   "body": 25.15625,
   "feedback": "acceptable",
   "hum": 90.200004578,
   "light": 25,
   "move_type": "work",
   "outdoor_des": "broken clouds",
   "outdoor_hum": 74,
   "outdoor_press": 100.8,
   "outdoor_temp": 27.980000000000018,
   "press": 100.800003052,
   "set_fanspeed": 2,
   "set_temp": 25,
   "stepNo": 23,
   "temp": 25.700000763,
   "time": "2020-05-09 19:54:39.469605"
  },
  {
   "body": 25.206249237,
   "feedback": "acceptable",
   "hum": 90.400001526,
   "light": 25,
   "move_type": "work",
   "outdoor_des": "broken clouds",
   "outdoor_hum": 74,
   "outdoor_press": 100.8,
   "outdoor_temp": 27.99000000000001,
   "press": 100.800003052,
   "set_fanspeed": 2,
   "set_temp": 25,
   "stepNo": 24,
   "temp": 25.700000763,
   "time": "2020-05-09 19:55:44.579243"
  },
  {
   "body": 25.262500763,
   "feedback": "acceptable",
   "hum": 90.599998474,
   "light": 25,
   "move_type": "work",
   "outdoor_des": "broken clouds",
   "outdoor_hum": 74,
   "outdoor_press": 100.8,
   "outdoor_temp": 27.980000000000018,
   "press": 100.800003052,
   "set_fanspeed": 2,
   "set_temp": 25,
   "stepNo": 25,
   "temp": 25.800001144,
   "time": "2020-05-09 19:56:49.789806"
  },
  {
   "body": 25.3125,
   "feedback": "acceptable",
   "hum": 90.700004578,
   "light": 25,
   "move_type": "work",
   "outdoor_des": "broken clouds",
   "outdoor_hum": 74,
   "outdoor_press": 100.8,
   "outdoor_temp": 27.99000000000001,
   "press": 100.800003052,
   "set_fanspeed": 2,
   "set_temp": 25,
   "stepNo": 26,
   "temp": 25.899999619,
   "time": "2020-05-09 19:57:56.261452"
  },
  {
   "body": 25.375,
   "feedback": "acceptable",
   "hum": 90.800003052,
   "light": 25,
   "move_type": "work",
   "outdoor_des": "broken clouds",
   "outdoor_hum": 74,
   "outdoor_press": 100.8,
   "outdoor_temp": 27.99000000000001,
   "press": 100.800003052,
   "set_fanspeed": 2,
   "set_temp": 25,
   "stepNo": 27,
   "temp": 26,
   "time": "2020-05-09 19:59:00.623226"
  },
  {
   "body": 25.418750763,
   "feedback": "acceptable",
   "hum": 90.700004578,
   "light": 25,
   "move_type": "work",
   "outdoor_des": "broken clouds",
   "outdoor_hum": 74,
   "outdoor_press": 100.8,
   "outdoor_temp": 27.980000000000018,
   "press": 100.800003052,
   "set_fanspeed": 2,
   "set_temp": 25,
   "stepNo": 28,
   "temp": 26,
   "time": "2020-05-09 20:00:06.087786"
  },
  {
   "body": 25.431249619,
   "feedback": "acceptable",
   "hum": 81.099998474,
   "light": 25.833328247,
   "move_type": "work",
   "outdoor_des": "broken clouds",
   "outdoor_hum": 74,
   "outdoor_press": 100.8,
   "outdoor_temp": 27.980000000000018,
   "press": 100.800003052,
   "set_fanspeed": 2,
   "set_temp": 25,
   "stepNo": 29,
   "temp": 25.800001144,
   "time": "2020-05-09 20:01:11.053365"
  },
  {
   "body": 25.331249237,
   "feedback": "acceptable",
   "hum": 73.099998474,
   "light": 25.833328247,
   "move_type": "work",
   "outdoor_des": "broken clouds",
   "outdoor_hum": 74,
   "outdoor_press": 100.8,
   "outdoor_temp": 27.980000000000018,
   "press": 100.800003052,
   "set_fanspeed": 2,
   "set_temp": 22,
   "stepNo": 30,
   "temp": 25.5,
   "time": "2020-05-09 20:02:16.843647"
  },
  {
   "body": 25.192708969,
   "feedback": "acceptable",
   "hum": 80.900001526,
   "light": 25,
   "move_type": "work",
   "outdoor_des": "broken clouds",
   "outdoor_hum": 74,
   "outdoor_press": 100.8,
   "outdoor_temp": 27.980000000000018,
   "press": 100.800003052,
   "set_fanspeed": 2,
   "set_temp": 22,
   "stepNo": 31,
   "temp": 25.300001144,
   "time": "2020-05-09 20:03:30.300528"
  },
  {
   "body": 25.200000763,
   "feedback": "acceptable",
   "hum": 84.599998474,
   "light": 25.833328247,
   "move_type": "work",
   "outdoor_des": "broken clouds",
   "outdoor_hum": 74,
   "outdoor_press": 100.8,
   "outdoor_temp": 27.980000000000018,
   "press": 100.800003052,
   "set_fanspeed": 2,
   "set_temp": 22,
   "stepNo": 32,
   "temp": 25.399999619,
   "time": "2020-05-09 20:04:36.231267"
  },
  {
   "body": 25.25,
   "feedback": "acceptable",
   "hum": 84.099998474,
   "light": 25,
   "move_type": "work",
   "outdoor_des": "broken clouds",
   "outdoor_hum": 74,
   "outdoor_press": 100.8,
   "outdoor_temp": 27.980000000000018,
   "press": 100.800003052,
   "set_fanspeed": 2,
   "set_temp": 22,
   "stepNo": 33,
   "temp": 25.5,
   "time": "2020-05-09 20:05:40.868192"
  },
  {
   "body": 25.237499237,
   "feedback": "acceptable",
   "hum": 74.300003052,
   "light": 25,
   "move_type": "work",
   "outdoor_des": "broken clouds",
   "outdoor_hum": 74,
   "outdoor_press": 100.8,
   "outdoor_temp": 27.980000000000018,
   "press": 100.800003052,
   "set_fanspeed": 2,
   "set_temp": 22,
   "stepNo": 34,
   "temp": 25.300001144,
   "time": "2020-05-09 20:06:46.575531"
  },
  {
   "body": 25.079545975,
   "feedback": "acceptable",
   "hum": 68.400001526,
   "light": 25.833328247,
   "move_type": "work",
   "outdoor_des": "broken clouds",
   "outdoor_hum": 74,
   "outdoor_press": 100.8,
   "outdoor_temp": 27.980000000000018,
   "press": 100.800003052,
   "set_fanspeed": 2,
   "set_temp": 22,
   "stepNo": 35,
   "temp": 25,
   "time": "2020-05-09 20:07:51.609341"
  },
  {
   "body": 24.887500763,
   "feedback": "acceptable",
   "hum": 64.800003052,
   "light": 25.833328247,
   "move_type": "work",
   "outdoor_des": "broken clouds",
   "outdoor_hum": 74,
   "outdoor_press": 100.8,
   "outdoor_temp": 27.980000000000018,
   "press": 100.800003052,
   "set_fanspeed": 2,
   "set_temp": 22,
   "stepNo": 36,
   "temp": 24.700000763,
   "time": "2020-05-09 20:08:57.006622"
  },
  {
   "body": 24.693750381,
   "feedback": "acceptable",
   "hum": 61.700000763,
   "light": 25,
   "move_type": "work",
   "outdoor_des": "broken clouds",
   "outdoor_hum": 74,
   "outdoor_press": 100.8,
   "outdoor_temp": 27.980000000000018,
   "press": 100.800003052,
   "set_fanspeed": 2,
   "set_temp": 22,
   "stepNo": 37,
   "temp": 24.5,
   "time": "2020-05-09 20:10:03.224921"
  },
  {
   "body": 24.505681992,
   "feedback": "acceptable",
   "hum": 60.200000763,
   "light": 25,
   "move_type": "work",
   "outdoor_des": "broken clouds",
   "outdoor_hum": 74,
   "outdoor_press": 100.8,
   "outdoor_temp": 27.980000000000018,
   "press": 100.800003052,
   "set_fanspeed": 2,
   "set_temp": 22,
   "stepNo": 38,
   "temp": 24.200000763,
   "time": "2020-05-09 20:11:09.002093"
  },
  {
   "body": 24.368749619,
   "feedback": "acceptable",
   "hum": 70.200004578,
   "light": 25.833328247,
   "move_type": "work",
   "outdoor_des": "broken clouds",
   "outdoor_hum": 74,
   "outdoor_press": 100.8,
   "outdoor_temp": 27.980000000000018,
   "press": 100.800003052,
   "set_fanspeed": 2,
   "set_temp": 22,
   "stepNo": 39,
   "temp": 24.100000381,
   "time": "2020-05-09 20:12:14.029594"
  },
  {
   "body": 24.386363983,
   "feedback": "acceptable",
   "hum": 76.700004578,
   "light": 25.833328247,
   "move_type": "work",
   "outdoor_des": "broken clouds",
   "outdoor_hum": 74,
   "outdoor_press": 100.8,
   "outdoor_temp": 27.980000000000018,
   "press": 100.800003052,
   "set_fanspeed": 2,
   "set_temp": 22,
   "stepNo": 40,
   "temp": 24.300001144,
   "time": "2020-05-09 20:13:21.322254"
  },
  {
   "body": 24.450000763,
   "feedback": "acceptable",
   "hum": 79.200004578,
   "light": 25,
   "move_type": "work",
   "outdoor_des": "broken clouds",
   "outdoor_hum": 79,
   "outdoor_press": 100.8,
   "outdoor_temp": 27.99000000000001,
   "press": 100.800003052,
   "set_fanspeed": 2,
   "set_temp": 22,
   "stepNo": 41,
   "temp": 24.5,
   "time": "2020-05-09 20:14:26.032628"
  },
  {
   "body": 24.471590042,
   "feedback": "acceptable",
   "hum": 70.700004578,
   "light": 25,
   "move_type": "work",
   "outdoor_des": "broken clouds",
   "outdoor_hum": 74,
   "outdoor_press": 100.8,
   "outdoor_temp": 27.980000000000018,
   "press": 100.800003052,
   "set_fanspeed": 2,
   "set_temp": 22,
   "stepNo": 42,
   "temp": 24.5,
   "time": "2020-05-09 20:15:32.502527"
  },
  {
   "body": 24.325000763,
   "feedback": "acceptable",
   "hum": 65.300003052,
   "light": 25.833328247,
   "move_type": "work",
   "outdoor_des": "broken clouds",
   "outdoor_hum": 79,
   "outdoor_press": 100.8,
   "outdoor_temp": 27.99000000000001,
   "press": 100.800003052,
   "set_fanspeed": 2,
   "set_temp": 22,
   "stepNo": 43,
   "temp": 24.200000763,
   "time": "2020-05-09 20:16:38.844112"
  },
  {
   "body": 24.164772034,
   "feedback": "acceptable",
   "hum": 61.900001526,
   "light": 25.833328247,
   "move_type": "work",
   "outdoor_des": "broken clouds",
   "outdoor_hum": 79,
   "outdoor_press": 100.8,
   "outdoor_temp": 27.99000000000001,
   "press": 100.800003052,
   "set_fanspeed": 2,
   "set_temp": 22,
   "stepNo": 44,
   "temp": 24,
   "time": "2020-05-09 20:17:44.337070"
  },
  {
   "body": 23.987499237,
   "feedback": "acceptable",
   "hum": 60,
   "light": 25.833328247,
   "move_type": "work",
   "outdoor_des": "broken clouds",
   "outdoor_hum": 79,
   "outdoor_press": 100.8,
   "outdoor_temp": 27.99000000000001,
   "press": 100.800003052,
   "set_fanspeed": 1,
   "set_temp": 23,
   "stepNo": 45,
   "temp": 23.700000763,
   "time": "2020-05-09 20:18:49.982350"
  },
  {
   "body": 23.864583969,
   "feedback": "acceptable",
   "hum": 70.800003052,
   "light": 25.833328247,
   "move_type": "work",
   "outdoor_des": "broken clouds",
   "outdoor_hum": 79,
   "outdoor_press": 100.8,
   "outdoor_temp": 27.99000000000001,
   "press": 100.800003052,
   "set_fanspeed": 1,
   "set_temp": 23,
   "stepNo": 46,
   "temp": 23.800001144,
   "time": "2020-05-09 20:20:03.107658"
  },
  {
   "body": 23.918750763,
   "feedback": "acceptable",
   "hum": 76.200004578,
   "light": 25.833328247,
   "move_type": "work",
   "outdoor_des": "broken clouds",
   "outdoor_hum": 79,
   "outdoor_press": 100.8,
   "outdoor_temp": 27.99000000000001,
   "press": 100.800003052,
   "set_fanspeed": 1,
   "set_temp": 23,
   "stepNo": 47,
   "temp": 24,
   "time": "2020-05-09 20:21:11.414106"
  },
  {
   "body": 24,
   "feedback": "acceptable",
   "hum": 79.5,
   "light": 25,
   "move_type": "work",
   "outdoor_des": "broken clouds",
   "outdoor_hum": 79,
   "outdoor_press": 100.8,
   "outdoor_temp": 27.99000000000001,
   "press": 100.800003052,
   "set_fanspeed": 1,
   "set_temp": 23,
   "stepNo": 48,
   "temp": 24.100000381,
   "time": "2020-05-09 20:22:16.948174"
  },
  {
   "body": 24.100000381,
   "feedback": "acceptable",
   "hum": 82.200004578,
   "light": 25,
   "move_type": "work",
   "outdoor_des": "broken clouds",
   "outdoor_hum": 79,
   "outdoor_press": 100.8,
   "outdoor_temp": 27.99000000000001,
   "press": 100.800003052,
   "set_fanspeed": 1,
   "set_temp": 23,
   "stepNo": 49,
   "temp": 24.399999619,
   "time": "2020-05-09 20:23:22.749871"
  },
  {
   "body": 24.210227966,
   "feedback": "acceptable",
   "hum": 79.599998474,
   "light": 25,
   "move_type": "work",
   "outdoor_des": "broken clouds",
   "outdoor_hum": 79,
   "outdoor_press": 100.8,
   "outdoor_temp": 28.0,
   "press": 100.800003052,
   "set_fanspeed": 1,
   "set_temp": 23,
   "stepNo": 50,
   "temp": 24.5,
   "time": "2020-05-09 20:24:28.034053"
  },
  {
   "body": 24.225000381,
   "feedback": "acceptable",
   "hum": 71.099998474,
   "light": 25,
   "move_type": "work",
   "outdoor_des": "broken clouds",
   "outdoor_hum": 79,
   "outdoor_press": 100.8,
   "outdoor_temp": 28.0,
   "press": 100.800003052,
   "set_fanspeed": 1,
   "set_temp": 23,
   "stepNo": 51,
   "temp": 24.399999619,
   "time": "2020-05-09 20:25:32.517450"
  },
  {
   "body": 24.137500763,
   "feedback": "acceptable",
   "hum": 65.5,
   "light": 25.833328247,
   "move_type": "work",
   "outdoor_des": "broken clouds",
   "outdoor_hum": 79,
   "outdoor_press": 100.8,
   "outdoor_temp": 28.0,
   "press": 100.800003052,
   "set_fanspeed": 1,
   "set_temp": 23,
   "stepNo": 52,
   "temp": 24.200000763,
   "time": "2020-05-09 20:26:38.678654"
  },
  {
   "body": 24.006250381,
   "feedback": "acceptable",
   "hum": 70.599998474,
   "light": 25.833328247,
   "move_type": "work",
   "outdoor_des": "broken clouds",
   "outdoor_hum": 79,
   "outdoor_press": 100.8,
   "outdoor_temp": 28.0,
   "press": 100.800003052,
   "set_fanspeed": 1,
   "set_temp": 23,
   "stepNo": 53,
   "temp": 24,
   "time": "2020-05-09 20:27:46.952090"
  },
  {
   "body": 24,
   "feedback": "acceptable",
   "hum": 76.700004578,
   "light": 25,
   "move_type": "work",
   "outdoor_des": "broken clouds",
   "outdoor_hum": 79,
   "outdoor_press": 100.8,
   "outdoor_temp": 28.0,
   "press": 100.800003052,
   "set_fanspeed": 1,
   "set_temp": 23,
   "stepNo": 54,
   "temp": 24.200000763,
   "time": "2020-05-09 20:28:52.390980"
  },
  {
   "body": 24.049999237,
   "feedback": "acceptable",
   "hum": 80.400001526,
   "light": 25.833328247,
   "move_type": "work",
   "outdoor_des": "broken clouds",
   "outdoor_hum": 79,
   "outdoor_press": 100.8,
   "outdoor_temp": 28.0,
   "press": 100.800003052,
   "set_fanspeed": 1,
   "set_temp": 23,
   "stepNo": 55,
   "temp": 24.300001144,
   "time": "2020-05-09 20:29:56.949408"
  },
  {
   "body": 24.137500763,
   "feedback": "acceptable",
   "hum": 82.900001526,
   "light": 25.833328247,
   "move_type": "work",
   "outdoor_des": "broken clouds",
   "outdoor_hum": 79,
   "outdoor_press": 100.8,
   "outdoor_temp": 28.0,
   "press": 100.800003052,
   "set_fanspeed": 1,
   "set_temp": 23,
   "stepNo": 56,
   "temp": 24.5,
   "time": "2020-05-09 20:31:02.935273"
  },
  {
   "body": 24.200000763,
   "feedback": "acceptable",
   "hum": 76.700004578,
   "light": 25,
   "move_type": "work",
   "outdoor_des": "broken clouds",
   "outdoor_hum": 79,
   "outdoor_press": 100.8,
   "outdoor_temp": 28.0,
   "press": 100.800003052,
   "set_fanspeed": 1,
   "set_temp": 23,
   "stepNo": 57,
   "temp": 24.5,
   "time": "2020-05-09 20:32:08.733504"
  },
  {
   "body": 24.174999237,
   "feedback": "acceptable",
   "hum": 68.800003052,
   "light": 25.833328247,
   "move_type": "work",
   "outdoor_des": "broken clouds",
   "outdoor_hum": 79,
   "outdoor_press": 100.8,
   "outdoor_temp": 27.99000000000001,
   "press": 100.800003052,
   "set_fanspeed": 1,
   "set_temp": 23,
   "stepNo": 58,
   "temp": 24.399999619,
   "time": "2020-05-09 20:33:17.138265"
  },
  {
   "body": 24.0625,
   "feedback": "acceptable",
   "hum": 63.799999237,
   "light": 25.833328247,
   "move_type": "work",
   "outdoor_des": "broken clouds",
   "outdoor_hum": 79,
   "outdoor_press": 100.8,
   "outdoor_temp": 27.99000000000001,
   "press": 100.800003052,
   "set_fanspeed": 1,
   "set_temp": 23,
   "stepNo": 59,
   "temp": 24,
   "time": "2020-05-09 20:34:24.094814"
  },
  {
   "body": 24,
   "feedback": "acceptable",
   "hum": 72.5,
   "light": 25.833328247,
   "move_type": "work",
   "outdoor_des": "broken clouds",
   "outdoor_hum": 79,
   "outdoor_press": 100.8,
   "outdoor_temp": 27.99000000000001,
   "press": 100.800003052,
   "set_fanspeed": 1,
   "set_temp": 23,
   "stepNo": 60,
   "temp": 23.899999619,
   "time": "2020-05-09 20:35:28.488799"
  }
 ]
}